[
    {
        "type": 10,
        "content": "## <:kristal:916793966287003690> **5.** Listen to the staff."
    },
    {
        "type": 17,
        "accent_color": null,
        "spoiler": false,
        "components": [
            {
                "type": 10,
                "content": "- No matter what, you must follow our requests.\n- We reserve the right to remove you at any point.\n- If you think something may break the rules, please do not try to handle it yourself. Message a staff member, or ping the staff role (<@&899157346465509417>)."
            }
        ]
    }
]